{
    "name": "My Book Room",
    "bookshelves": [
        {
            "books": [
                {
                    "author": "George R R Martin",
                    "review": "Very good!",
                    "rating": 9,
                    "genre": "FANTASY",
                    "title": "Game of Thrones"
                },
                {
                    "author": "JK Rowling",
                    "review": "Not bad!",
                    "rating": 8,
                    "genre": "YOUNG_ADULT",
                    "title": "Harry Potter"
                }
            ],
            "label": "All Books"
        },
        {
            "books": [{
                "author": "JK Rowling",
                "review": "Not bad!",
                "rating": 8,
                "genre": "YOUNG_ADULT",
                "title": "Harry Potter"
            }],
            "label": "To Read"
        },
        {
            "books": [{
                "author": "George R R Martin",
                "review": "Very good!",
                "rating": 9,
                "genre": "FANTASY",
                "title": "Game of Thrones"
            }],
            "label": "Completed"
        }
    ]
}